nanotts/__init__.py
nanotts-0.0.1.dist-info/LICENSE
nanotts-0.0.1.dist-info/METADATA
nanotts-0.0.1.dist-info/WHEEL
nanotts-0.0.1.dist-info/top_level.txt
nanotts-0.0.1.dist-info/RECORD
