Metadata-Version: 2.1
Name: nanotts
Version: 0.0.1
Summary: Python wrapper for the NanoTTS speech synthesizer
Home-page: https://github.com/VolkaRacho/nanotts
Author: Volker Austrup
Author-email: volkeraustrup@gmail.com
License: UNKNOWN
Platform: UNKNOWN
Classifier: Topic :: Multimedia :: Sound/Audio :: Sound Synthesis
Classifier: Topic :: Multimedia :: Sound/Audio :: Speech
Classifier: Programming Language :: Python :: 3
Classifier: License :: OSI Approved :: MIT License
Classifier: Operating System :: POSIX :: Linux
Requires-Python: >=3.6
